clean_python/__init__.py
clean_python/py.typed
clean_python/amqp/__init__.py
clean_python/amqp/celery_rmq_broker.py
clean_python/api_client/__init__.py
clean_python/api_client/api_gateway.py
clean_python/api_client/api_provider.py
clean_python/api_client/exceptions.py
clean_python/api_client/files.py
clean_python/api_client/response.py
clean_python/api_client/sync_api_provider.py
clean_python/base/__init__.py
clean_python/base/application/__init__.py
clean_python/base/application/manage.py
clean_python/base/domain/__init__.py
clean_python/base/domain/context.py
clean_python/base/domain/domain_event.py
clean_python/base/domain/domain_service.py
clean_python/base/domain/exceptions.py
clean_python/base/domain/filter.py
clean_python/base/domain/gateway.py
clean_python/base/domain/pagination.py
clean_python/base/domain/provider.py
clean_python/base/domain/repository.py
clean_python/base/domain/root_entity.py
clean_python/base/domain/types.py
clean_python/base/domain/value.py
clean_python/base/domain/value_object.py
clean_python/base/infrastructure/__init__.py
clean_python/base/infrastructure/in_memory_gateway.py
clean_python/base/infrastructure/internal_gateway.py
clean_python/base/infrastructure/lru_cache.py
clean_python/base/infrastructure/mapper.py
clean_python/base/infrastructure/tmpdir_provider.py
clean_python/base/infrastructure/typed_internal_gateway.py
clean_python/base/presentation/__init__.py
clean_python/base/presentation/link.py
clean_python/blinker/__init__.py
clean_python/blinker/blinker_event_provider.py
clean_python/celery/__init__.py
clean_python/celery/base_task.py
clean_python/celery/celery_task_logger.py
clean_python/celery/config.py
clean_python/celery/kubernetes.py
clean_python/fastapi/__init__.py
clean_python/fastapi/error_responses.py
clean_python/fastapi/fastapi_access_logger.py
clean_python/fastapi/request_query.py
clean_python/fastapi/resource.py
clean_python/fastapi/schema.py
clean_python/fastapi/security.py
clean_python/fastapi/service.py
clean_python-0.20.2.dist-info/LICENSE
clean_python-0.20.2.dist-info/METADATA
clean_python-0.20.2.dist-info/WHEEL
clean_python-0.20.2.dist-info/top_level.txt
clean_python-0.20.2.dist-info/RECORD
