Metadata-Version: 2.2
Name: clean-python
Version: 0.20.2
Summary: Clean architecture in Python
Author-email: Nelen & Schuurmans <info@nelen-schuurmans.nl>
License: Proprietary
Project-URL: homepage, https://github.com/nens/clean-python
Classifier: Programming Language :: Python
Requires-Python: >=3.10
License-File: LICENSE
Requires-Dist: pydantic>=2.9
Requires-Dist: inject>=5
Requires-Dist: asgiref>=3.8
Requires-Dist: async-lru>=2.0
Requires-Dist: backoff>=2.2
Requires-Dist: pyyaml>=6.0.1
Provides-Extra: test
Requires-Dist: pytest; extra == "test"
Requires-Dist: pytest-cov; extra == "test"
Requires-Dist: pytest-asyncio==0.21.*; extra == "test"
Requires-Dist: debugpy; extra == "test"
Requires-Dist: httpx; extra == "test"
Requires-Dist: uvicorn; extra == "test"
Requires-Dist: python-multipart; extra == "test"
Requires-Dist: pytest-celery<1; extra == "test"
Requires-Dist: packaging; extra == "test"
Provides-Extra: fastapi
Requires-Dist: fastapi>=0.115; extra == "fastapi"
Provides-Extra: auth
Requires-Dist: pyjwt[crypto]>=2.9; extra == "auth"
Provides-Extra: amqp
Requires-Dist: pika>=1.3; extra == "amqp"
Provides-Extra: blinker
Requires-Dist: blinker>=1.8; extra == "blinker"
Provides-Extra: celery
Requires-Dist: celery>=5.4; extra == "celery"
Provides-Extra: fluentbit
Requires-Dist: fluent-logger; extra == "fluentbit"
Provides-Extra: sql
Requires-Dist: sqlalchemy>=2; extra == "sql"
Requires-Dist: asyncpg>=0.30; extra == "sql"
Requires-Dist: greenlet>=3; extra == "sql"
Provides-Extra: sql-sync
Requires-Dist: sqlalchemy>=2; extra == "sql-sync"
Provides-Extra: s3
Requires-Dist: aioboto3>=13.1; extra == "s3"
Requires-Dist: types-aioboto3[s3]; extra == "s3"
Provides-Extra: s3-sync
Requires-Dist: boto3>=1.34.70; extra == "s3-sync"
Requires-Dist: boto3-stubs[s3]; extra == "s3-sync"
Provides-Extra: api-client
Requires-Dist: aiohttp>=3.10; extra == "api-client"
Requires-Dist: urllib3>=2.0.2; extra == "api-client"
Provides-Extra: profiler
Requires-Dist: yappi; extra == "profiler"
Provides-Extra: debugger
Requires-Dist: debugpy; extra == "debugger"
Provides-Extra: nanoid
Requires-Dist: nanoid>=2; extra == "nanoid"
